channest/VERSION.txt
channest/__init__.py
channest/__main__.py
channest/_utils.py
channest/api.py
channest/heights.py
channest/polygonize.py
channest/skeletonize.py
channest/summarize.py
channest/widths.py
channest/gridbased/__init__.py
channest/qc/__init__.py
channest/qc/fences.py
channest/qc/layerheightplot.py
channest/qc/layerwidthplot.py
channest/qc/scatterwidthheight.py
channest/qc/sliceplot.py
channest/qc/stacking.py
channest-1.0.dist-info/LICENSE
channest-1.0.dist-info/METADATA
channest-1.0.dist-info/WHEEL
channest-1.0.dist-info/top_level.txt
channest-1.0.dist-info/RECORD
