Metadata-Version: 2.1
Name: channest
Version: 1.0
Summary: Package for estimating channel parameters for ResQml models converted by nrresqml
Home-page: https://github.com/NorskRegnesentral/channest
Author: Norwegian Computing Center
License: GPL-3.0
Platform: UNKNOWN
Classifier: Programming Language :: Python :: 3
Classifier: Programming Language :: Python :: 3.7
Classifier: License :: OSI Approved :: GNU General Public License v3 (GPLv3)
Classifier: Operating System :: OS Independent
Requires-Python: >=3.7
